performance/__init__.py
performance/heimdall.py
performance/manager.py
performance/version.py
performance/base/__init__.py
performance/base/baseThread.py
performance/controller/__init__.py
performance/controller/performance_server.py
performance/hrof/__init__.py
performance/hrof/conv_hprof.py
performance/hrof/pull_hprof.py
performance/memory/__init__.py
performance/memory/record.py
heimdall_android-0.0.7.dist-info/METADATA
heimdall_android-0.0.7.dist-info/WHEEL
heimdall_android-0.0.7.dist-info/entry_points.txt
heimdall_android-0.0.7.dist-info/top_level.txt
heimdall_android-0.0.7.dist-info/RECORD
