Metadata-Version: 2.1
Name: heimdall-android
Version: 0.0.7
Summary: UNKNOWN
Home-page: https://github.com
Author: HBQA
License: UNKNOWN
Platform: UNKNOWN
Classifier: Programming Language :: Python :: 3 :: Only
Classifier: Programming Language :: Python :: 3.6
Classifier: License :: OSI Approved :: MIT License
Classifier: Operating System :: MacOS
